{
  "schema_version": 2,
  "pipeline_version": 5,
  "matte_mode_requested": "author_alpha",
  "matte_mode_used": "author_alpha",
  "import_source": "robin-solo",
  "robin_id": "prism.act041_centered_calm",
  "pose_id": "prism_041_act041_centered_calm",
  "runtime_id": 41,
  "source_pack": "prism",
  "cols": 147,
  "rows": 208,
  "block_size_detected": 4,
  "palette": [
    [
      0,
      0,
      0,
      0
    ],
    [
      0,
      0,
      0,
      255
    ],
    [
      65,
      74,
      52,
      255
    ],
    [
      70,
      83,
      58,
      255
    ],
    [
      76,
      90,
      62,
      255
    ],
    [
      51,
      60,
      44,
      255
    ],
    [
      35,
      76,
      44,
      255
    ],
    [
      30,
      73,
      40,
      255
    ],
    [
      37,
      82,
      46,
      255
    ],
    [
      30,
      71,
      39,
      255
    ],
    [
      31,
      21,
      11,
      255
    ],
    [
      104,
      102,
      74,
      255
    ],
    [
      148,
      128,
      102,
      255
    ],
    [
      33,
      75,
      42,
      255
    ],
    [
      23,
      63,
      32,
      255
    ],
    [
      26,
      60,
      32,
      255
    ],
    [
      26,
      64,
      34,
      255
    ],
    [
      20,
      52,
      26,
      255
    ],
    [
      19,
      56,
      27,
      255
    ],
    [
      27,
      66,
      36,
      255
    ],
    [
      30,
      70,
      38,
      255
    ],
    [
      27,
      69,
      37,
      255
    ],
    [
      26,
      67,
      35,
      255
    ],
    [
      28,
      68,
      36,
      255
    ],
    [
      31,
      75,
      41,
      255
    ],
    [
      22,
      60,
      30,
      255
    ],
    [
      26,
      66,
      34,
      255
    ],
    [
      23,
      61,
      31,
      255
    ],
    [
      56,
      42,
      28,
      255
    ],
    [
      15,
      44,
      20,
      255
    ],
    [
      16,
      48,
      22,
      255
    ],
    [
      22,
      56,
      29,
      255
    ],
    [
      17,
      51,
      24,
      255
    ],
    [
      14,
      40,
      18,
      255
    ],
    [
      9,
      32,
      13,
      255
    ],
    [
      11,
      39,
      16,
      255
    ],
    [
      0,
      4,
      0,
      255
    ],
    [
      5,
      2,
      0,
      255
    ],
    [
      5,
      12,
      3,
      255
    ],
    [
      23,
      11,
      2,
      255
    ],
    [
      6,
      24,
      8,
      255
    ],
    [
      44,
      25,
      9,
      255
    ],
    [
      95,
      55,
      27,
      255
    ],
    [
      65,
      30,
      7,
      255
    ],
    [
      142,
      83,
      43,
      255
    ],
    [
      164,
      53,
      1,
      255
    ],
    [
      197,
      63,
      0,
      255
    ],
    [
      142,
      74,
      32,
      255
    ],
    [
      155,
      91,
      46,
      255
    ],
    [
      224,
      83,
      1,
      255
    ],
    [
      221,
      76,
      1,
      255
    ],
    [
      233,
      89,
      1,
      255
    ],
    [
      230,
      84,
      1,
      255
    ],
    [
      239,
      91,
      1,
      255
    ],
    [
      234,
      84,
      1,
      255
    ],
    [
      152,
      108,
      72,
      255
    ],
    [
      138,
      164,
      63,
      255
    ]
  ],
  "anchor": [
    73,
    207
  ],
  "source_sha256": null,
  "foreground_cells": 19248,
  "runtime_size": [
    960,
    540
  ],
  "paths": {
    "isolated": "isolated.png",
    "graph_render": "graph-render.png",
    "preview": "preview.png",
    "runtime_frame": "runtime-960x540.png"
  },
  "cells_len": 30576
}