{
  "schema_version": 2,
  "pipeline_version": 5,
  "matte_mode_requested": "author_alpha",
  "matte_mode_used": "author_alpha",
  "import_source": "robin-solo",
  "robin_id": "speech.fly045_joyful_flight",
  "pose_id": "speech_145_fly045_joyful_flight",
  "runtime_id": 145,
  "source_pack": "speech",
  "cols": 160,
  "rows": 160,
  "block_size_detected": 5,
  "palette": [
    [
      0,
      0,
      0,
      0
    ],
    [
      242,
      119,
      1,
      255
    ],
    [
      208,
      124,
      48,
      255
    ],
    [
      227,
      102,
      1,
      255
    ],
    [
      198,
      85,
      4,
      255
    ],
    [
      145,
      129,
      115,
      255
    ],
    [
      124,
      107,
      93,
      255
    ],
    [
      120,
      86,
      56,
      255
    ],
    [
      73,
      81,
      105,
      255
    ],
    [
      120,
      59,
      12,
      255
    ],
    [
      73,
      53,
      40,
      255
    ],
    [
      52,
      61,
      84,
      255
    ],
    [
      50,
      46,
      47,
      255
    ],
    [
      31,
      59,
      117,
      255
    ],
    [
      29,
      49,
      86,
      255
    ],
    [
      26,
      40,
      67,
      255
    ],
    [
      31,
      36,
      45,
      255
    ],
    [
      2,
      54,
      171,
      255
    ],
    [
      4,
      50,
      124,
      255
    ],
    [
      0,
      45,
      148,
      255
    ],
    [
      3,
      45,
      104,
      255
    ],
    [
      0,
      41,
      141,
      255
    ],
    [
      0,
      39,
      129,
      255
    ],
    [
      3,
      40,
      94,
      255
    ],
    [
      0,
      36,
      120,
      255
    ],
    [
      0,
      33,
      111,
      255
    ],
    [
      1,
      33,
      97,
      255
    ],
    [
      8,
      34,
      71,
      255
    ],
    [
      2,
      33,
      74,
      255
    ],
    [
      0,
      33,
      73,
      255
    ],
    [
      42,
      23,
      10,
      255
    ],
    [
      20,
      18,
      18,
      255
    ],
    [
      8,
      26,
      52,
      255
    ],
    [
      8,
      15,
      26,
      255
    ],
    [
      2,
      28,
      68,
      255
    ],
    [
      3,
      25,
      55,
      255
    ],
    [
      3,
      19,
      42,
      255
    ],
    [
      3,
      12,
      24,
      255
    ],
    [
      1,
      29,
      70,
      255
    ],
    [
      1,
      25,
      57,
      255
    ],
    [
      1,
      19,
      45,
      255
    ],
    [
      1,
      10,
      24,
      255
    ],
    [
      0,
      29,
      86,
      255
    ],
    [
      0,
      29,
      69,
      255
    ],
    [
      0,
      26,
      84,
      255
    ],
    [
      0,
      25,
      70,
      255
    ],
    [
      0,
      27,
      63,
      255
    ],
    [
      0,
      25,
      60,
      255
    ],
    [
      0,
      23,
      59,
      255
    ],
    [
      0,
      22,
      53,
      255
    ],
    [
      0,
      20,
      59,
      255
    ],
    [
      0,
      20,
      49,
      255
    ],
    [
      0,
      17,
      41,
      255
    ],
    [
      0,
      14,
      39,
      255
    ],
    [
      0,
      13,
      30,
      255
    ],
    [
      0,
      8,
      21,
      255
    ],
    [
      0,
      0,
      0,
      255
    ]
  ],
  "anchor": [
    80,
    159
  ],
  "source_sha256": null,
  "foreground_cells": 7300,
  "runtime_size": [
    960,
    540
  ],
  "paths": {
    "isolated": "isolated.png",
    "graph_render": "graph-render.png",
    "preview": "preview.png",
    "runtime_frame": "runtime-960x540.png"
  },
  "cells_len": 25600
}