{
  "schema_version": 2,
  "pipeline_version": 5,
  "matte_mode_requested": "author_alpha",
  "matte_mode_used": "author_alpha",
  "import_source": "robin-solo",
  "robin_id": "prism.int027_present_screen_left",
  "pose_id": "prism_175_int027_present_screen_left",
  "runtime_id": 175,
  "source_pack": "prism",
  "cols": 231,
  "rows": 240,
  "block_size_detected": 3,
  "palette": [
    [
      0,
      0,
      0,
      0
    ],
    [
      0,
      0,
      0,
      255
    ],
    [
      33,
      47,
      18,
      255
    ],
    [
      26,
      31,
      10,
      255
    ],
    [
      63,
      86,
      41,
      255
    ],
    [
      86,
      156,
      43,
      255
    ],
    [
      1,
      99,
      17,
      255
    ],
    [
      15,
      112,
      31,
      255
    ],
    [
      59,
      51,
      39,
      255
    ],
    [
      1,
      79,
      8,
      255
    ],
    [
      17,
      99,
      28,
      255
    ],
    [
      1,
      87,
      12,
      255
    ],
    [
      4,
      87,
      15,
      255
    ],
    [
      2,
      76,
      9,
      255
    ],
    [
      1,
      57,
      3,
      255
    ],
    [
      5,
      67,
      11,
      255
    ],
    [
      2,
      54,
      3,
      255
    ],
    [
      1,
      26,
      0,
      255
    ],
    [
      1,
      74,
      7,
      255
    ],
    [
      5,
      76,
      14,
      255
    ],
    [
      1,
      41,
      1,
      255
    ],
    [
      1,
      32,
      1,
      255
    ],
    [
      4,
      13,
      1,
      255
    ],
    [
      2,
      45,
      2,
      255
    ],
    [
      0,
      66,
      4,
      255
    ],
    [
      1,
      70,
      5,
      255
    ],
    [
      1,
      37,
      1,
      255
    ],
    [
      16,
      21,
      3,
      255
    ],
    [
      12,
      0,
      0,
      255
    ],
    [
      2,
      61,
      5,
      255
    ],
    [
      36,
      18,
      5,
      255
    ],
    [
      60,
      33,
      13,
      255
    ],
    [
      84,
      49,
      25,
      255
    ],
    [
      27,
      8,
      0,
      255
    ],
    [
      1,
      50,
      1,
      255
    ],
    [
      99,
      51,
      20,
      255
    ],
    [
      118,
      72,
      40,
      255
    ],
    [
      0,
      64,
      3,
      255
    ],
    [
      171,
      114,
      72,
      255
    ],
    [
      82,
      29,
      2,
      255
    ],
    [
      164,
      51,
      5,
      255
    ],
    [
      191,
      87,
      25,
      255
    ],
    [
      158,
      99,
      57,
      255
    ],
    [
      249,
      98,
      2,
      255
    ],
    [
      54,
      16,
      1,
      255
    ],
    [
      0,
      60,
      2,
      255
    ],
    [
      63,
      23,
      2,
      255
    ],
    [
      0,
      53,
      1,
      255
    ],
    [
      191,
      73,
      11,
      255
    ],
    [
      248,
      91,
      1,
      255
    ],
    [
      2,
      67,
      7,
      255
    ],
    [
      195,
      156,
      126,
      255
    ],
    [
      248,
      85,
      1,
      255
    ],
    [
      243,
      76,
      0,
      255
    ],
    [
      29,
      38,
      11,
      255
    ],
    [
      79,
      69,
      44,
      255
    ],
    [
      0,
      46,
      1,
      255
    ]
  ],
  "anchor": [
    115,
    239
  ],
  "source_sha256": null,
  "foreground_cells": 24477,
  "runtime_size": [
    960,
    540
  ],
  "paths": {
    "isolated": "isolated.png",
    "graph_render": "graph-render.png",
    "preview": "preview.png",
    "runtime_frame": "runtime-960x540.png"
  },
  "cells_len": 55440
}