{
  "schema_version": 2,
  "pipeline_version": 5,
  "matte_mode_requested": "author_alpha",
  "matte_mode_used": "author_alpha",
  "pose_id": "wizardjoe_250_final_recovery_home",
  "runtime_id": 250,
  "source_pack": "wizardjoe",
  "cols": 185,
  "rows": 224,
  "block_size_detected": 5,
  "palette": [
    [
      0,
      0,
      0,
      0
    ],
    [
      78,
      120,
      132,
      255
    ],
    [
      0,
      126,
      212,
      255
    ],
    [
      1,
      122,
      207,
      255
    ],
    [
      1,
      119,
      196,
      255
    ],
    [
      0,
      120,
      204,
      255
    ],
    [
      0,
      124,
      209,
      255
    ],
    [
      0,
      110,
      192,
      255
    ],
    [
      0,
      122,
      207,
      255
    ],
    [
      0,
      123,
      208,
      255
    ],
    [
      0,
      117,
      200,
      255
    ],
    [
      0,
      88,
      162,
      255
    ],
    [
      0,
      121,
      207,
      255
    ],
    [
      0,
      118,
      204,
      255
    ],
    [
      4,
      84,
      156,
      255
    ],
    [
      1,
      133,
      147,
      255
    ],
    [
      3,
      108,
      163,
      255
    ],
    [
      0,
      123,
      207,
      255
    ],
    [
      127,
      162,
      83,
      255
    ],
    [
      252,
      211,
      0,
      255
    ],
    [
      248,
      196,
      6,
      255
    ],
    [
      17,
      81,
      160,
      255
    ],
    [
      0,
      121,
      205,
      255
    ],
    [
      250,
      195,
      0,
      255
    ],
    [
      246,
      138,
      18,
      255
    ],
    [
      214,
      185,
      78,
      255
    ],
    [
      249,
      213,
      17,
      255
    ],
    [
      247,
      173,
      28,
      255
    ],
    [
      6,
      62,
      122,
      255
    ],
    [
      62,
      87,
      120,
      255
    ],
    [
      171,
      93,
      26,
      255
    ],
    [
      0,
      22,
      47,
      255
    ],
    [
      40,
      38,
      44,
      255
    ],
    [
      58,
      62,
      125,
      255
    ],
    [
      0,
      0,
      0,
      255
    ],
    [
      216,
      148,
      50,
      255
    ],
    [
      117,
      64,
      27,
      255
    ],
    [
      150,
      81,
      20,
      255
    ],
    [
      139,
      73,
      16,
      255
    ],
    [
      159,
      89,
      29,
      255
    ],
    [
      101,
      50,
      35,
      255
    ],
    [
      117,
      62,
      9,
      255
    ],
    [
      250,
      171,
      97,
      255
    ],
    [
      218,
      103,
      22,
      255
    ],
    [
      247,
      157,
      51,
      255
    ],
    [
      231,
      31,
      65,
      255
    ],
    [
      219,
      41,
      28,
      255
    ],
    [
      151,
      22,
      55,
      255
    ],
    [
      232,
      39,
      1,
      255
    ],
    [
      234,
      56,
      9,
      255
    ],
    [
      181,
      37,
      104,
      255
    ],
    [
      212,
      28,
      65,
      255
    ],
    [
      2,
      151,
      42,
      255
    ],
    [
      2,
      141,
      38,
      255
    ],
    [
      26,
      143,
      110,
      255
    ],
    [
      202,
      83,
      18,
      255
    ],
    [
      228,
      24,
      108,
      255
    ]
  ],
  "anchor": [
    91,
    223
  ],
  "bbox_source": [
    168,
    69,
    1085,
    1185
  ],
  "source_sha256": "eae6d83c86e0b7a7e2f4e178cc126768852bb479171b266b077f2fde5593aa91",
  "foreground_cells": 21888,
  "runtime_size": [
    960,
    540
  ],
  "paths": {
    "isolated": "isolated.png",
    "graph_render": "graph-render.png",
    "preview": "preview.png",
    "runtime_frame": "runtime-960x540.png"
  },
  "cells_len": 41440
}