{
  "schema_version": 2,
  "pipeline_version": 5,
  "matte_mode_requested": "author_alpha",
  "matte_mode_used": "author_alpha",
  "pose_id": "wizardjoe_002_turn_front_3q_left",
  "runtime_id": 2,
  "source_pack": "wizardjoe",
  "cols": 170,
  "rows": 224,
  "block_size_detected": 5,
  "palette": [
    [
      0,
      0,
      0,
      0
    ],
    [
      44,
      94,
      146,
      255
    ],
    [
      2,
      130,
      205,
      255
    ],
    [
      1,
      136,
      210,
      255
    ],
    [
      50,
      58,
      98,
      255
    ],
    [
      25,
      27,
      33,
      255
    ],
    [
      1,
      95,
      162,
      255
    ],
    [
      1,
      124,
      200,
      255
    ],
    [
      1,
      131,
      208,
      255
    ],
    [
      15,
      126,
      170,
      255
    ],
    [
      2,
      125,
      195,
      255
    ],
    [
      2,
      127,
      204,
      255
    ],
    [
      1,
      84,
      148,
      255
    ],
    [
      1,
      121,
      193,
      255
    ],
    [
      2,
      90,
      149,
      255
    ],
    [
      1,
      112,
      188,
      255
    ],
    [
      1,
      125,
      203,
      255
    ],
    [
      2,
      75,
      128,
      255
    ],
    [
      1,
      128,
      204,
      255
    ],
    [
      240,
      203,
      23,
      255
    ],
    [
      252,
      207,
      3,
      255
    ],
    [
      138,
      92,
      51,
      255
    ],
    [
      210,
      177,
      49,
      255
    ],
    [
      206,
      161,
      44,
      255
    ],
    [
      1,
      131,
      206,
      255
    ],
    [
      46,
      158,
      82,
      255
    ],
    [
      8,
      92,
      138,
      255
    ],
    [
      245,
      164,
      81,
      255
    ],
    [
      96,
      56,
      34,
      255
    ],
    [
      1,
      131,
      196,
      255
    ],
    [
      0,
      30,
      56,
      255
    ],
    [
      199,
      133,
      55,
      255
    ],
    [
      2,
      58,
      106,
      255
    ],
    [
      2,
      76,
      158,
      255
    ],
    [
      249,
      179,
      36,
      255
    ],
    [
      171,
      101,
      37,
      255
    ],
    [
      143,
      80,
      26,
      255
    ],
    [
      135,
      75,
      20,
      255
    ],
    [
      156,
      88,
      27,
      255
    ],
    [
      185,
      107,
      42,
      255
    ],
    [
      72,
      30,
      22,
      255
    ],
    [
      122,
      67,
      17,
      255
    ],
    [
      111,
      56,
      28,
      255
    ],
    [
      89,
      46,
      10,
      255
    ],
    [
      241,
      150,
      47,
      255
    ],
    [
      190,
      61,
      43,
      255
    ],
    [
      235,
      53,
      8,
      255
    ],
    [
      234,
      102,
      16,
      255
    ],
    [
      223,
      31,
      82,
      255
    ],
    [
      195,
      28,
      52,
      255
    ],
    [
      222,
      34,
      4,
      255
    ],
    [
      148,
      19,
      43,
      255
    ],
    [
      0,
      0,
      0,
      255
    ],
    [
      4,
      146,
      64,
      255
    ],
    [
      2,
      138,
      160,
      255
    ],
    [
      221,
      33,
      110,
      255
    ],
    [
      230,
      33,
      109,
      255
    ]
  ],
  "anchor": [
    84,
    223
  ],
  "bbox_source": [
    160,
    69,
    1006,
    1185
  ],
  "source_sha256": "af0c2e7e823e41f5b56f25d4c2ffdc51ca71ac62db5dea6168d9a30616a10334",
  "foreground_cells": 22116,
  "runtime_size": [
    960,
    540
  ],
  "paths": {
    "isolated": "isolated.png",
    "graph_render": "graph-render.png",
    "preview": "preview.png",
    "runtime_frame": "runtime-960x540.png"
  },
  "cells_len": 38080
}