{
  "schema_version": 2,
  "pipeline_version": 5,
  "matte_mode_requested": "author_alpha",
  "matte_mode_used": "author_alpha",
  "pose_id": "wizardjoe_206_magic_cast_recoil",
  "runtime_id": 206,
  "source_pack": "wizardjoe",
  "cols": 204,
  "rows": 219,
  "block_size_detected": 5,
  "palette": [
    [
      0,
      0,
      0,
      0
    ],
    [
      176,
      100,
      33,
      255
    ],
    [
      152,
      90,
      26,
      255
    ],
    [
      216,
      182,
      95,
      255
    ],
    [
      152,
      83,
      20,
      255
    ],
    [
      142,
      77,
      21,
      255
    ],
    [
      137,
      73,
      13,
      255
    ],
    [
      165,
      89,
      24,
      255
    ],
    [
      203,
      109,
      37,
      255
    ],
    [
      214,
      130,
      41,
      255
    ],
    [
      250,
      172,
      103,
      255
    ],
    [
      121,
      67,
      21,
      255
    ],
    [
      91,
      49,
      15,
      255
    ],
    [
      84,
      38,
      13,
      255
    ],
    [
      113,
      55,
      32,
      255
    ],
    [
      28,
      30,
      29,
      255
    ],
    [
      118,
      165,
      116,
      255
    ],
    [
      77,
      130,
      122,
      255
    ],
    [
      1,
      124,
      208,
      255
    ],
    [
      0,
      124,
      209,
      255
    ],
    [
      49,
      96,
      136,
      255
    ],
    [
      0,
      120,
      201,
      255
    ],
    [
      0,
      112,
      198,
      255
    ],
    [
      1,
      78,
      150,
      255
    ],
    [
      0,
      101,
      178,
      255
    ],
    [
      0,
      116,
      200,
      255
    ],
    [
      0,
      88,
      165,
      255
    ],
    [
      0,
      109,
      194,
      255
    ],
    [
      1,
      74,
      138,
      255
    ],
    [
      1,
      63,
      119,
      255
    ],
    [
      0,
      78,
      148,
      255
    ],
    [
      18,
      60,
      115,
      255
    ],
    [
      211,
      151,
      37,
      255
    ],
    [
      250,
      196,
      6,
      255
    ],
    [
      251,
      210,
      19,
      255
    ],
    [
      0,
      71,
      135,
      255
    ],
    [
      1,
      69,
      131,
      255
    ],
    [
      11,
      73,
      135,
      255
    ],
    [
      4,
      101,
      147,
      255
    ],
    [
      7,
      47,
      82,
      255
    ],
    [
      0,
      60,
      114,
      255
    ],
    [
      0,
      47,
      87,
      255
    ],
    [
      1,
      57,
      105,
      255
    ],
    [
      203,
      32,
      34,
      255
    ],
    [
      215,
      63,
      20,
      255
    ],
    [
      179,
      20,
      8,
      255
    ],
    [
      218,
      34,
      13,
      255
    ],
    [
      203,
      24,
      60,
      255
    ],
    [
      209,
      42,
      22,
      255
    ],
    [
      208,
      96,
      19,
      255
    ],
    [
      248,
      165,
      29,
      255
    ],
    [
      0,
      0,
      0,
      255
    ],
    [
      8,
      152,
      53,
      255
    ],
    [
      143,
      20,
      46,
      255
    ],
    [
      2,
      128,
      119,
      255
    ],
    [
      177,
      17,
      84,
      255
    ],
    [
      209,
      26,
      101,
      255
    ]
  ],
  "anchor": [
    101,
    218
  ],
  "bbox_source": [
    74,
    70,
    1089,
    1161
  ],
  "source_sha256": "ecc2c85009da6d4120de0cb4fb37b763e0f3800604376e79115331a159023c96",
  "foreground_cells": 22267,
  "runtime_size": [
    960,
    540
  ],
  "paths": {
    "isolated": "isolated.png",
    "graph_render": "graph-render.png",
    "preview": "preview.png",
    "runtime_frame": "runtime-960x540.png"
  },
  "cells_len": 44676
}