{
  "schema_version": 2,
  "pipeline_version": 5,
  "matte_mode_requested": "author_alpha",
  "matte_mode_used": "author_alpha",
  "pose_id": "wizardjoe_092_emotion_sadness",
  "runtime_id": 92,
  "source_pack": "wizardjoe",
  "cols": 179,
  "rows": 224,
  "block_size_detected": 5,
  "palette": [
    [
      0,
      0,
      0,
      0
    ],
    [
      42,
      83,
      122,
      255
    ],
    [
      15,
      122,
      176,
      255
    ],
    [
      1,
      134,
      215,
      255
    ],
    [
      50,
      54,
      99,
      255
    ],
    [
      0,
      83,
      149,
      255
    ],
    [
      0,
      115,
      193,
      255
    ],
    [
      1,
      131,
      211,
      255
    ],
    [
      1,
      129,
      210,
      255
    ],
    [
      1,
      86,
      153,
      255
    ],
    [
      0,
      130,
      212,
      255
    ],
    [
      2,
      82,
      137,
      255
    ],
    [
      1,
      132,
      214,
      255
    ],
    [
      0,
      127,
      208,
      255
    ],
    [
      1,
      130,
      211,
      255
    ],
    [
      1,
      128,
      208,
      255
    ],
    [
      250,
      182,
      1,
      255
    ],
    [
      249,
      204,
      13,
      255
    ],
    [
      253,
      202,
      1,
      255
    ],
    [
      31,
      24,
      25,
      255
    ],
    [
      238,
      158,
      22,
      255
    ],
    [
      232,
      166,
      108,
      255
    ],
    [
      156,
      157,
      72,
      255
    ],
    [
      95,
      55,
      44,
      255
    ],
    [
      103,
      53,
      7,
      255
    ],
    [
      173,
      95,
      28,
      255
    ],
    [
      187,
      98,
      29,
      255
    ],
    [
      202,
      115,
      38,
      255
    ],
    [
      239,
      160,
      95,
      255
    ],
    [
      1,
      78,
      135,
      255
    ],
    [
      1,
      116,
      190,
      255
    ],
    [
      1,
      134,
      197,
      255
    ],
    [
      0,
      129,
      211,
      255
    ],
    [
      87,
      44,
      14,
      255
    ],
    [
      140,
      84,
      48,
      255
    ],
    [
      128,
      68,
      11,
      255
    ],
    [
      223,
      139,
      24,
      255
    ],
    [
      39,
      159,
      98,
      255
    ],
    [
      132,
      69,
      20,
      255
    ],
    [
      165,
      90,
      28,
      255
    ],
    [
      154,
      83,
      18,
      255
    ],
    [
      0,
      28,
      50,
      255
    ],
    [
      1,
      56,
      100,
      255
    ],
    [
      0,
      129,
      209,
      255
    ],
    [
      237,
      178,
      66,
      255
    ],
    [
      0,
      0,
      0,
      255
    ],
    [
      8,
      55,
      101,
      255
    ],
    [
      124,
      59,
      40,
      255
    ],
    [
      205,
      29,
      56,
      255
    ],
    [
      220,
      41,
      30,
      255
    ],
    [
      239,
      46,
      6,
      255
    ],
    [
      234,
      68,
      20,
      255
    ],
    [
      239,
      40,
      83,
      255
    ],
    [
      124,
      20,
      44,
      255
    ],
    [
      5,
      153,
      39,
      255
    ],
    [
      4,
      140,
      152,
      255
    ],
    [
      236,
      34,
      109,
      255
    ]
  ],
  "anchor": [
    88,
    223
  ],
  "bbox_source": [
    93,
    69,
    980,
    1185
  ],
  "source_sha256": "2afa411ae69144fa8076e9d8e1316c6820d5481825294e7ea831dd90c3503a92",
  "foreground_cells": 22324,
  "runtime_size": [
    960,
    540
  ],
  "paths": {
    "isolated": "isolated.png",
    "graph_render": "graph-render.png",
    "preview": "preview.png",
    "runtime_frame": "runtime-960x540.png"
  },
  "cells_len": 40096
}