{
  "schema_version": 2,
  "pipeline_version": 5,
  "matte_mode_requested": "author_alpha",
  "matte_mode_used": "author_alpha",
  "import_source": "robin-solo",
  "robin_id": "prism.int019_robinspeech_interrupts_politely",
  "pose_id": "prism_166_int019_robinspeech_interrupts_politely",
  "runtime_id": 166,
  "source_pack": "prism",
  "cols": 160,
  "rows": 160,
  "block_size_detected": 5,
  "palette": [
    [
      0,
      0,
      0,
      0
    ],
    [
      158,
      122,
      94,
      255
    ],
    [
      142,
      95,
      61,
      255
    ],
    [
      234,
      79,
      1,
      255
    ],
    [
      194,
      79,
      11,
      255
    ],
    [
      65,
      117,
      35,
      255
    ],
    [
      64,
      85,
      43,
      255
    ],
    [
      87,
      78,
      45,
      255
    ],
    [
      3,
      78,
      21,
      255
    ],
    [
      233,
      70,
      1,
      255
    ],
    [
      215,
      70,
      0,
      255
    ],
    [
      157,
      71,
      20,
      255
    ],
    [
      42,
      70,
      33,
      255
    ],
    [
      3,
      70,
      17,
      255
    ],
    [
      1,
      70,
      16,
      255
    ],
    [
      179,
      62,
      8,
      255
    ],
    [
      64,
      61,
      35,
      255
    ],
    [
      4,
      64,
      14,
      255
    ],
    [
      4,
      60,
      13,
      255
    ],
    [
      4,
      58,
      11,
      255
    ],
    [
      1,
      65,
      13,
      255
    ],
    [
      1,
      63,
      12,
      255
    ],
    [
      1,
      60,
      12,
      255
    ],
    [
      1,
      58,
      11,
      255
    ],
    [
      1,
      58,
      8,
      255
    ],
    [
      1,
      56,
      9,
      255
    ],
    [
      145,
      47,
      3,
      255
    ],
    [
      83,
      43,
      15,
      255
    ],
    [
      71,
      35,
      12,
      255
    ],
    [
      51,
      41,
      29,
      255
    ],
    [
      51,
      20,
      2,
      255
    ],
    [
      12,
      50,
      16,
      255
    ],
    [
      3,
      52,
      9,
      255
    ],
    [
      25,
      32,
      17,
      255
    ],
    [
      34,
      15,
      2,
      255
    ],
    [
      21,
      15,
      6,
      255
    ],
    [
      19,
      7,
      0,
      255
    ],
    [
      1,
      54,
      10,
      255
    ],
    [
      1,
      54,
      6,
      255
    ],
    [
      1,
      52,
      8,
      255
    ],
    [
      1,
      50,
      9,
      255
    ],
    [
      1,
      50,
      5,
      255
    ],
    [
      1,
      48,
      6,
      255
    ],
    [
      1,
      45,
      5,
      255
    ],
    [
      1,
      40,
      4,
      255
    ],
    [
      1,
      32,
      2,
      255
    ],
    [
      1,
      19,
      1,
      255
    ],
    [
      1,
      0,
      0,
      255
    ],
    [
      0,
      0,
      0,
      255
    ]
  ],
  "anchor": [
    80,
    159
  ],
  "source_sha256": null,
  "foreground_cells": 6322,
  "runtime_size": [
    960,
    540
  ],
  "paths": {
    "isolated": "isolated.png",
    "graph_render": "graph-render.png",
    "preview": "preview.png",
    "runtime_frame": "runtime-960x540.png"
  },
  "cells_len": 25600
}