{
  "schema_version": 2,
  "pipeline_version": 5,
  "matte_mode_requested": "author_alpha",
  "matte_mode_used": "author_alpha",
  "pose_id": "wizardjoe_130_write_in_book",
  "runtime_id": 130,
  "source_pack": "wizardjoe",
  "cols": 165,
  "rows": 223,
  "block_size_detected": 5,
  "palette": [
    [
      0,
      0,
      0,
      0
    ],
    [
      159,
      159,
      88,
      255
    ],
    [
      21,
      117,
      150,
      255
    ],
    [
      1,
      91,
      166,
      255
    ],
    [
      2,
      116,
      182,
      255
    ],
    [
      1,
      123,
      206,
      255
    ],
    [
      22,
      87,
      140,
      255
    ],
    [
      247,
      227,
      194,
      255
    ],
    [
      1,
      105,
      178,
      255
    ],
    [
      0,
      111,
      193,
      255
    ],
    [
      1,
      115,
      197,
      255
    ],
    [
      1,
      81,
      144,
      255
    ],
    [
      0,
      124,
      207,
      255
    ],
    [
      1,
      70,
      131,
      255
    ],
    [
      0,
      83,
      149,
      255
    ],
    [
      1,
      120,
      203,
      255
    ],
    [
      0,
      120,
      204,
      255
    ],
    [
      65,
      157,
      96,
      255
    ],
    [
      250,
      201,
      16,
      255
    ],
    [
      220,
      172,
      27,
      255
    ],
    [
      248,
      186,
      1,
      255
    ],
    [
      2,
      87,
      148,
      255
    ],
    [
      167,
      91,
      29,
      255
    ],
    [
      155,
      113,
      69,
      255
    ],
    [
      0,
      88,
      169,
      255
    ],
    [
      245,
      211,
      99,
      255
    ],
    [
      225,
      197,
      124,
      255
    ],
    [
      0,
      26,
      55,
      255
    ],
    [
      1,
      49,
      93,
      255
    ],
    [
      210,
      154,
      62,
      255
    ],
    [
      20,
      66,
      127,
      255
    ],
    [
      20,
      46,
      79,
      255
    ],
    [
      124,
      80,
      46,
      255
    ],
    [
      121,
      68,
      24,
      255
    ],
    [
      136,
      73,
      16,
      255
    ],
    [
      129,
      68,
      13,
      255
    ],
    [
      110,
      56,
      8,
      255
    ],
    [
      116,
      63,
      19,
      255
    ],
    [
      33,
      26,
      23,
      255
    ],
    [
      112,
      56,
      31,
      255
    ],
    [
      150,
      79,
      21,
      255
    ],
    [
      156,
      86,
      29,
      255
    ],
    [
      80,
      42,
      9,
      255
    ],
    [
      89,
      52,
      24,
      255
    ],
    [
      228,
      118,
      28,
      255
    ],
    [
      250,
      174,
      85,
      255
    ],
    [
      203,
      91,
      23,
      255
    ],
    [
      207,
      47,
      28,
      255
    ],
    [
      239,
      41,
      5,
      255
    ],
    [
      242,
      56,
      5,
      255
    ],
    [
      222,
      28,
      74,
      255
    ],
    [
      247,
      153,
      63,
      255
    ],
    [
      195,
      24,
      52,
      255
    ],
    [
      0,
      0,
      0,
      255
    ],
    [
      121,
      16,
      39,
      255
    ],
    [
      7,
      149,
      38,
      255
    ],
    [
      4,
      139,
      64,
      255
    ]
  ],
  "anchor": [
    81,
    222
  ],
  "bbox_source": [
    169,
    69,
    986,
    1180
  ],
  "source_sha256": "86547b802a84e66823616c47fb6829645bbba6c2ce94de532ad2e8cd2c24c80f",
  "foreground_cells": 20793,
  "runtime_size": [
    960,
    540
  ],
  "paths": {
    "isolated": "isolated.png",
    "graph_render": "graph-render.png",
    "preview": "preview.png",
    "runtime_frame": "runtime-960x540.png"
  },
  "cells_len": 36795
}